ab_core/pkce/__init__.py
ab_core/pkce/methods/__init__.py
ab_core/pkce/methods/base.py
ab_core/pkce/methods/plain.py
ab_core/pkce/methods/s256.py
ab_core/pkce/methods/template.py
ab_core/pkce/schema/__init__.py
ab_core/pkce/schema/pkce_method.py
ab_pkce-0.1.5.dist-info/METADATA
ab_pkce-0.1.5.dist-info/WHEEL
ab_pkce-0.1.5.dist-info/licenses/LICENSE
ab_pkce-0.1.5.dist-info/RECORD
