Metadata-Version: 2.4
Name: ab-pkce
Version: 0.1.5
Author-email: Matthew Coulter <53892067+mattcoulter7@users.noreply.github.com>
License-File: LICENSE
Requires-Python: <4,>=3.12
Requires-Dist: pydantic<3,>=2.11.7
